{
  "META": {
    "repoName": "Takahashi's Favorite Repo",
    "repoIcon": "https://raw.githubusercontent.com/TakahashiNguyen/TakahashiNguyen/main/myAvater.jpg"
  },
  "Games": [
    {
      "name": "Flappy Bird",
      "version": "4.3",
      "icon": "https://raw.githubusercontent.com/brandonplank/flappybird/main/Flappy%20Bird/Assets.xcassets/AppLogo.imageset/1024.png",
      "down": "https://github.com/brandonplank/flappybird/releases/download/4.3/org.brandonplank.flappybird.ipa",
      "category": "Games",
      "description": "",
      "bundleID": "com.game.flappybird",
      "contact": {
        "web": "https://github.com/brandonplank/flappybird",
      }
    },
  ],
  "Tweaked": [],
  "Jailbreaks": [],
  "Emulators": [
    {
      "name": "Delta",
      "version": "1.4",
      "icon": "https://raw.githubusercontent.com/rileytestut/Delta/main/Resources/Assets.xcassets/AppIcon.appiconset/icon-1024.png",
      "down": "https://github.com/rileytestut/Delta/releases/download/v1.4/Delta_1_4.ipa",
      "category": "Emulators",
      "description": "",
      "bundleID": "com.emulator.Delta",
      "contact": {
        "web": "https://github.com/rileytestut/Delta",
      }
    },
  ],
  "Other": []
}
